README.md
setup.py
hwy/__init__.py
hwy/hellowy.py
hwy.egg-info/PKG-INFO
hwy.egg-info/SOURCES.txt
hwy.egg-info/dependency_links.txt
hwy.egg-info/entry_points.txt
hwy.egg-info/top_level.txt